{"Timestamp":"2023-04-21T14:59:25.2983105+02:00","Level":"Information","MessageTemplate":"Add User successfuly created: Name:AdministradorDefault , Address:RandomAddress 123, UserType:Admin ,  Role:admin, Email:admin@default.com, Phone:333-333","Properties":{"SourceContext":"Sat.Recruitment.Api.Services.UserService","MachineName":"DESKTOP-B2HS1Q8","ProcessId":5072,"ThreadId":1,"ApplicationName":"Serilog.WebApplication"}}
{"Timestamp":"2023-04-21T14:59:25.3299059+02:00","Level":"Information","MessageTemplate":"User File is empty","Properties":{"SourceContext":"Sat.Recruitment.Api.Repository.UserRepository","MachineName":"DESKTOP-B2HS1Q8","ProcessId":5072,"ThreadId":6,"ApplicationName":"Serilog.WebApplication"}}
{"Timestamp":"2023-04-21T14:59:25.3890720+02:00","Level":"Error","MessageTemplate":"User already exists, duplicated user found","Properties":{"SourceContext":"Sat.Recruitment.Api.Repository.UserRepository","MachineName":"DESKTOP-B2HS1Q8","ProcessId":5072,"ThreadId":6,"ApplicationName":"Serilog.WebApplication"}}
{"Timestamp":"2023-04-21T14:59:48.8799984+02:00","Level":"Information","MessageTemplate":"User File is empty","Properties":{"SourceContext":"Sat.Recruitment.Api.Repository.UserRepository","ActionId":"0dfaff11-e4be-47db-8ebb-68b606cfa163","ActionName":"Sat.Recruitment.Api.Controllers.LoginController.Login (Sat.Recruitment.Api)","RequestId":"0HMQ2D0U4JEOQ:00000005","RequestPath":"/Login","SpanId":"|30ff0577-4780a251d1ca92ab.","TraceId":"30ff0577-4780a251d1ca92ab","ParentId":"","ConnectionId":"0HMQ2D0U4JEOQ","MachineName":"DESKTOP-B2HS1Q8","ProcessId":5072,"ThreadId":8,"ApplicationName":"Serilog.WebApplication"}}
{"Timestamp":"2023-04-21T14:59:48.9094888+02:00","Level":"Information","MessageTemplate":"HTTP {RequestMethod} {RequestPath} responded {StatusCode} in {Elapsed:0.0000} ms","Properties":{"RequestMethod":"POST","RequestPath":"/Login","StatusCode":200,"Elapsed":81.9608,"SourceContext":"Serilog.AspNetCore.RequestLoggingMiddleware","RequestId":"0HMQ2D0U4JEOQ:00000005","SpanId":"|30ff0577-4780a251d1ca92ab.","TraceId":"30ff0577-4780a251d1ca92ab","ParentId":"","ConnectionId":"0HMQ2D0U4JEOQ","MachineName":"DESKTOP-B2HS1Q8","ProcessId":5072,"ThreadId":7,"ApplicationName":"Serilog.WebApplication"},"Renderings":{"Elapsed":[{"Format":"0.0000","Rendering":"81.9608"}]}}
{"Timestamp":"2023-04-21T15:00:43.4235966+02:00","Level":"Information","MessageTemplate":"HTTP {RequestMethod} {RequestPath} responded {StatusCode} in {Elapsed:0.0000} ms","Properties":{"RequestMethod":"POST","RequestPath":"/Users","StatusCode":403,"Elapsed":49.7854,"SourceContext":"Serilog.AspNetCore.RequestLoggingMiddleware","RequestId":"0HMQ2D0U4JEOQ:00000006","SpanId":"|30ff0578-4780a251d1ca92ab.","TraceId":"30ff0578-4780a251d1ca92ab","ParentId":"","ConnectionId":"0HMQ2D0U4JEOQ","MachineName":"DESKTOP-B2HS1Q8","ProcessId":5072,"ThreadId":12,"ApplicationName":"Serilog.WebApplication"},"Renderings":{"Elapsed":[{"Format":"0.0000","Rendering":"49.7854"}]}}
{"Timestamp":"2023-04-21T15:02:54.9740182+02:00","Level":"Information","MessageTemplate":"Application Starting on Development","Properties":{"MachineName":"DESKTOP-B2HS1Q8","ProcessId":8624,"ThreadId":1,"ApplicationName":"Serilog.WebApplication"}}
